celery_simple_schedule/__init__.py
celery_simple_schedule/core.py
celery_simple_schedule-0.2.1.dist-info/LICENSE
celery_simple_schedule-0.2.1.dist-info/METADATA
celery_simple_schedule-0.2.1.dist-info/WHEEL
celery_simple_schedule-0.2.1.dist-info/RECORD
