Metadata-Version: 2.3
Name: celery-simple-schedule
Version: 0.2.1
Summary: A lightweight Python utility that simplifies defining Celery Beat schedules using a clean, declarative function-based API.
License: MIT
Author: StanislavJPG
Author-email: samper.stas@gmail.com
Requires-Python: >=3.9
Classifier: License :: OSI Approved :: MIT License
Classifier: Programming Language :: Python :: 3
Classifier: Programming Language :: Python :: 3.9
Classifier: Programming Language :: Python :: 3.10
Classifier: Programming Language :: Python :: 3.11
Classifier: Programming Language :: Python :: 3.12
Classifier: Programming Language :: Python :: 3.13
